 {
  "products": [
    {
      "id": 1,
      "name": "스타일리시 원피스",
      "price": 89900,
      "image": "https://www.kbs-cdn.shop/image/product-default.jpg",
      "rating": 4.5,
      "category": "dress",
      "size": "M",
      "color": "블랙"
    },
    {
      "id": 2,
      "name": "클래식 셔츠",
      "price": 59900,
      "image": "https://www.kbs-cdn.shop/image/product-default.jpg",
      "rating": 4.3,
      "category": "top",
      "size": "L",
      "color": "블루"
    },
    {
      "id": 3,
      "name": "캐주얼 스니커즈",
      "price": 129900,
      "image": "https://www.kbs-cdn.shop/image/product-default.jpg",
      "rating": 4.7,
      "category": "shoes",
      "size": "250",
      "color": "블랙"
    },
    {
      "id": 4,
      "name": "레더 핸드백",
      "price": 199900,
      "image": "https://www.kbs-cdn.shop/image/product-default.jpg",
      "rating": 4.6,
      "category": "bag",
      "size": "L",
      "color": "블루"
    },
    {
      "id": 5,
      "name": "무선 이어폰",
      "price": 79900,
      "image": "https://www.kbs-cdn.shop/image/product-default.jpg",
      "rating": 4.4,
      "category": "accessories",
      "size": "M",
      "color": "블랙"
    },
    {
      "id": 6,
      "name": "스포츠 티셔츠",
      "price": 39900,
      "image": "https://www.kbs-cdn.shop/image/product-default.jpg",
      "rating": 4.2,
      "category": "top",
      "size": "M",
      "color": "블랙"
    },
    {
      "id": 7,
      "name": "미니멀 백팩",
      "price": 149900,
      "image": "https://www.kbs-cdn.shop/image/product-default.jpg",
      "rating": 4.8,
      "category": "bag",
      "size": "L",
      "color": "블루"
    },
    {
      "id": 8,
      "name": "데님 자켓",
      "price": 89900,
      "image": "https://www.kbs-cdn.shop/image/product-default.jpg",
      "rating": 4.5,
      "category": "jacket",
      "size": "M",
      "color": "블랙"
    }
  ]
}
